{
  "timestamp": "2025-12-12T23:15:24.660245",
  "run_name": "sweep_160bees_50plants_r0",
  "parameters": {
    "simulation_bounds": {
      "min": -500,
      "max": 500
    },
    "num_plants": 50,
    "num_bees": 160,
    "num_hives": 1,
    "bee_velocity_mean": 24,
    "bee_velocity_std": 1.0,
    "dt": 0.05,
    "max_steps": 1000,
    "attraction_strength": 0.4
  },
  "metrics": {
    "total_trips": 65,
    "total_pollen_collected": 3300.0,
    "avg_distance_per_bee": 2105.5417727597965,
    "avg_trips_per_bee": 0.40625,
    "total_plant_visits": 117,
    "plants_visited": 37,
    "plant_visitation_rate": 0.74,
    "avg_pollen_level": 0.34,
    "pollen_per_distance": 0.009795578632935977,
    "pollen_per_bee_per_step": 0.020625
  }
}