{
  "timestamp": "2025-12-12T11:46:39.619131",
  "run_name": "sweep_70bees_100plants_r8",
  "parameters": {
    "simulation_bounds": {
      "min": -500,
      "max": 500
    },
    "num_plants": 100,
    "num_bees": 70,
    "num_hives": 1,
    "bee_velocity_mean": 24,
    "bee_velocity_std": 1.0,
    "dt": 0.05,
    "max_steps": 1000,
    "attraction_strength": 0.4
  },
  "metrics": {
    "total_trips": 86,
    "total_pollen_collected": 3485.0,
    "avg_distance_per_bee": 1851.8062898994801,
    "avg_trips_per_bee": 1.2285714285714286,
    "total_plant_visits": 104,
    "plants_visited": 39,
    "plant_visitation_rate": 0.39,
    "avg_pollen_level": 0.6515000000000001,
    "pollen_per_distance": 0.02688494717685442,
    "pollen_per_bee_per_step": 0.04978571428571429
  }
}