{
  "timestamp": "2025-12-13T22:17:32.004881",
  "run_name": "sweep_40bees_100plants_r7",
  "parameters": {
    "simulation_bounds": {
      "min": -500,
      "max": 500
    },
    "num_plants": 100,
    "num_bees": 40,
    "num_hives": 2,
    "bee_velocity_mean": 24,
    "bee_velocity_std": 1.0,
    "dt": 0.05,
    "max_steps": 1000,
    "attraction_strength": 0.4
  },
  "metrics": {
    "total_trips": 71,
    "total_pollen_collected": 3215.0,
    "avg_distance_per_bee": 1609.2459189639821,
    "avg_trips_per_bee": 1.775,
    "total_plant_visits": 116,
    "plants_visited": 39,
    "plant_visitation_rate": 0.39,
    "avg_pollen_level": 0.6785000000000001,
    "pollen_per_distance": 0.04994575350655212,
    "pollen_per_bee_per_step": 0.080375
  }
}