{
  "timestamp": "2025-12-12T08:58:04.754111",
  "run_name": "sweep_40bees_100plants_r8",
  "parameters": {
    "simulation_bounds": {
      "min": -500,
      "max": 500
    },
    "num_plants": 100,
    "num_bees": 40,
    "num_hives": 2,
    "bee_velocity_mean": 24,
    "bee_velocity_std": 1.0,
    "dt": 0.05,
    "max_steps": 1000,
    "attraction_strength": 0.4
  },
  "metrics": {
    "total_trips": 79,
    "total_pollen_collected": 2920.0,
    "avg_distance_per_bee": 1815.6459922059125,
    "avg_trips_per_bee": 1.975,
    "total_plant_visits": 87,
    "plants_visited": 36,
    "plant_visitation_rate": 0.36,
    "avg_pollen_level": 0.708,
    "pollen_per_distance": 0.040206075585973076,
    "pollen_per_bee_per_step": 0.073
  }
}